jinni/__init__.py
jinni/cli.py
jinni/config_system.py
jinni/context_walker.py
jinni/core_logic.py
jinni/exceptions.py
jinni/exclusion_parser.py
jinni/file_processor.py
jinni/server.py
jinni/utils.py
jinni-0.4.0.dist-info/METADATA
jinni-0.4.0.dist-info/WHEEL
jinni-0.4.0.dist-info/entry_points.txt
jinni-0.4.0.dist-info/licenses/LICENSE
jinni-0.4.0.dist-info/RECORD
