Metadata-Version: 2.4
Name: jinni
Version: 0.4.0
Summary: A tool to help LLMs efficiently read and understand project context.
Project-URL: Homepage, https://github.com/smat-dev/jinni
Project-URL: Repository, https://github.com/smat-dev/jinni
Author-email: Solomon Matthews <dev@sdmatthews.com>
License: Apache-2.0
License-File: LICENSE
Classifier: Development Status :: 3 - Alpha
Classifier: Intended Audience :: Developers
Classifier: License :: OSI Approved :: Apache Software License
Classifier: Programming Language :: Python :: 3
Classifier: Programming Language :: Python :: 3.10
Classifier: Programming Language :: Python :: 3.11
Classifier: Programming Language :: Python :: 3.12
Classifier: Topic :: Software Development :: Libraries :: Python Modules
Classifier: Topic :: Utilities
Requires-Python: >=3.10
Requires-Dist: mcp
Requires-Dist: pathspec
Requires-Dist: pydantic
Requires-Dist: pyperclip
Requires-Dist: tiktoken
Provides-Extra: dev
Requires-Dist: pytest; extra == 'dev'
Requires-Dist: pytest-asyncio; extra == 'dev'
